python_xgraph/__init__.py
python_xgraph/graph.py
tests/__init__.py
tests/test_graph.py
python_xgraph-1.0.2.dist-info/LICENSE
python_xgraph-1.0.2.dist-info/METADATA
python_xgraph-1.0.2.dist-info/WHEEL
python_xgraph-1.0.2.dist-info/top_level.txt
python_xgraph-1.0.2.dist-info/RECORD
