Metadata-Version: 2.1
Name: python-xgraph
Version: 1.0.2
Summary: A simple graph library with DFS, BFS, and cycle detection.
Home-page: https://github.com/sinha-abhishek-ai/python-xGraph
Author: Abhishek Sinha
Author-email: sinha.abhishek.ai@gmail.com
License: MIT
Keywords: graph,DFS,BFS,cycle detection,topological sort
Classifier: Programming Language :: Python :: 3
Classifier: License :: OSI Approved :: MIT License
Classifier: Operating System :: OS Independent
Requires-Python: >=3.6
License-File: LICENSE
Provides-Extra: dev
Requires-Dist: pytest ; extra == 'dev'
Requires-Dist: black ; extra == 'dev'
Requires-Dist: flake8 ; extra == 'dev'
